hikkatl/__init__.py
hikkatl/custom.py
hikkatl/entitycache.py
hikkatl/functions.py
hikkatl/helpers.py
hikkatl/hints.py
hikkatl/password.py
hikkatl/requestiter.py
hikkatl/sync.py
hikkatl/types.py
hikkatl/utils.py
hikkatl/version.py
hikkatl/_updates/__init__.py
hikkatl/_updates/entitycache.py
hikkatl/_updates/messagebox.py
hikkatl/_updates/session.py
hikkatl/client/__init__.py
hikkatl/client/account.py
hikkatl/client/auth.py
hikkatl/client/bots.py
hikkatl/client/buttons.py
hikkatl/client/chats.py
hikkatl/client/dialogs.py
hikkatl/client/downloads.py
hikkatl/client/messageparse.py
hikkatl/client/messages.py
hikkatl/client/stories.py
hikkatl/client/telegrambaseclient.py
hikkatl/client/telegramclient.py
hikkatl/client/updates.py
hikkatl/client/uploads.py
hikkatl/client/users.py
hikkatl/crypto/__init__.py
hikkatl/crypto/aes.py
hikkatl/crypto/aesctr.py
hikkatl/crypto/authkey.py
hikkatl/crypto/cdndecrypter.py
hikkatl/crypto/factorization.py
hikkatl/crypto/libssl.py
hikkatl/crypto/rsa.py
hikkatl/errors/__init__.py
hikkatl/errors/common.py
hikkatl/errors/rpcbaseerrors.py
hikkatl/errors/rpcerrorlist.py
hikkatl/events/__init__.py
hikkatl/events/album.py
hikkatl/events/callbackquery.py
hikkatl/events/chataction.py
hikkatl/events/common.py
hikkatl/events/inlinequery.py
hikkatl/events/messagedeleted.py
hikkatl/events/messageedited.py
hikkatl/events/messageread.py
hikkatl/events/newmessage.py
hikkatl/events/raw.py
hikkatl/events/userupdate.py
hikkatl/extensions/__init__.py
hikkatl/extensions/binaryreader.py
hikkatl/extensions/html.py
hikkatl/extensions/markdown.py
hikkatl/extensions/messagepacker.py
hikkatl/network/__init__.py
hikkatl/network/authenticator.py
hikkatl/network/mtprotoplainsender.py
hikkatl/network/mtprotosender.py
hikkatl/network/mtprotostate.py
hikkatl/network/requeststate.py
hikkatl/network/connection/__init__.py
hikkatl/network/connection/connection.py
hikkatl/network/connection/http.py
hikkatl/network/connection/tcpabridged.py
Hikka_TL_New-2.0.8.dist-info/LICENSE
Hikka_TL_New-2.0.8.dist-info/METADATA
Hikka_TL_New-2.0.8.dist-info/WHEEL
Hikka_TL_New-2.0.8.dist-info/top_level.txt
Hikka_TL_New-2.0.8.dist-info/RECORD
